hg_evolve-12.0.0.dist-info/licenses/COPYING
hgext3rd/__init__.py
hgext3rd/pullbundle.py
hgext3rd/evolve/__init__.py
hgext3rd/evolve/cmdrewrite.py
hgext3rd/evolve/compat.py
hgext3rd/evolve/debugcmd.py
hgext3rd/evolve/depthcache.py
hgext3rd/evolve/evolvecmd.py
hgext3rd/evolve/exthelper.py
hgext3rd/evolve/firstmergecache.py
hgext3rd/evolve/genericcaches.py
hgext3rd/evolve/headchecking.py
hgext3rd/evolve/metadata.py
hgext3rd/evolve/obscache.py
hgext3rd/evolve/obsdiscovery.py
hgext3rd/evolve/obsexchange.py
hgext3rd/evolve/obshashtree.py
hgext3rd/evolve/obshistory.py
hgext3rd/evolve/revset.py
hgext3rd/evolve/rewind.py
hgext3rd/evolve/rewriteutil.py
hgext3rd/evolve/stablerange.py
hgext3rd/evolve/stablerangecache.py
hgext3rd/evolve/stablesort.py
hgext3rd/evolve/state.py
hgext3rd/evolve/templatekw.py
hgext3rd/evolve/utility.py
hgext3rd/evolve/thirdparty/__init__.py
hgext3rd/evolve/thirdparty/cbor.py
hgext3rd/topic/__init__.py
hgext3rd/topic/common.py
hgext3rd/topic/compat.py
hgext3rd/topic/constants.py
hgext3rd/topic/destination.py
hgext3rd/topic/discovery.py
hgext3rd/topic/evolvebits.py
hgext3rd/topic/flow.py
hgext3rd/topic/randomname.py
hgext3rd/topic/revset.py
hgext3rd/topic/server.py
hgext3rd/topic/stack.py
hgext3rd/topic/topicmap.py
hg_evolve-12.0.0.dist-info/METADATA
hg_evolve-12.0.0.dist-info/WHEEL
hg_evolve-12.0.0.dist-info/top_level.txt
hg_evolve-12.0.0.dist-info/RECORD
