Metadata-Version: 2.4
Name: hg-evolve
Version: 12.0.0
Summary: Flexible evolution of Mercurial history.
Home-page: https://www.mercurial-scm.org/doc/evolution/
Author: Pierre-Yves David
Author-email: pierre-yves.david@ens-lyon.org
Maintainer: Pierre-Yves David
Maintainer-email: pierre-yves.david@ens-lyon.org
License: GPLv2+
Keywords: hg mercurial
Requires-Python: >=3.6.2, <4
License-File: COPYING
Dynamic: author
Dynamic: author-email
Dynamic: description
Dynamic: description-content-type
Dynamic: home-page
Dynamic: keywords
Dynamic: license
Dynamic: license-file
Dynamic: maintainer
Dynamic: maintainer-email
Dynamic: requires-python
Dynamic: summary
